graphtimer/__init__.py
graphtimer/graph.py
graphtimer/graphtimer.py
graphtimer/plotter.py
graphtimer/timers.py
graphtimer-0.0.4.dist-info/LICENSE
graphtimer-0.0.4.dist-info/METADATA
graphtimer-0.0.4.dist-info/WHEEL
graphtimer-0.0.4.dist-info/top_level.txt
graphtimer-0.0.4.dist-info/RECORD
