Metadata-Version: 2.1
Name: graphtimer
Version: 0.0.4
Summary: Time code execution and graph results
Home-page: https://github.com/Peilonrayz/graphtimer
Author: Peilonrayz
Author-email: peilonrayz@gmail.com
License: MIT
Keywords: timer graph performance
Platform: UNKNOWN
Classifier: Development Status :: 3 - Alpha
Classifier: Intended Audience :: Developers
Classifier: License :: OSI Approved :: MIT License
Classifier: Operating System :: OS Independent
Classifier: Programming Language :: Python :: 3.7
Provides-Extra: base
Requires-Dist: matplotlib ; extra == 'base'
